rlemasklib/__init__.py
rlemasklib/_version.py
rlemasklib/boolfunc.py
rlemasklib/oop.py
rlemasklib/oop_cython.cp312-win_amd64.pyd
rlemasklib/oop_cython.pyx
rlemasklib/rlemasklib.py
rlemasklib/rlemasklib_cython.cp312-win_amd64.pyd
rlemasklib/rlemasklib_cython.pyx
rlemasklib/c/basics.c
rlemasklib/c/basics.h
rlemasklib/c/boolfuncs.c
rlemasklib/c/boolfuncs.h
rlemasklib/c/connected_components.c
rlemasklib/c/connected_components.h
rlemasklib/c/encode_decode.c
rlemasklib/c/encode_decode.h
rlemasklib/c/iou_nms.c
rlemasklib/c/iou_nms.h
rlemasklib/c/largest_interior_rectangle.c
rlemasklib/c/largest_interior_rectangle.h
rlemasklib/c/minmax.h
rlemasklib/c/misc.c
rlemasklib/c/misc.h
rlemasklib/c/moments.c
rlemasklib/c/moments.h
rlemasklib/c/pad_crop.c
rlemasklib/c/pad_crop.h
rlemasklib/c/shapes.c
rlemasklib/c/shapes.h
rlemasklib/c/single_translation_unit.c
rlemasklib/c/transpose_flip.c
rlemasklib/c/transpose_flip.h
rlemasklib/c/warp_affine.c
rlemasklib/c/warp_affine.h
rlemasklib/c/warp_common.c
rlemasklib/c/warp_common.h
rlemasklib/c/warp_distorted.c
rlemasklib/c/warp_distorted.h
rlemasklib/c/warp_perspective.c
rlemasklib/c/warp_perspective.h
rlemasklib-0.4.0.dist-info/licenses/LICENSE
rlemasklib-0.4.0.dist-info/METADATA
rlemasklib-0.4.0.dist-info/WHEEL
rlemasklib-0.4.0.dist-info/top_level.txt
rlemasklib-0.4.0.dist-info/RECORD
