Metadata-Version: 2.4
Name: RLEMaskLib
Version: 0.4.0
Summary: Manipulate run-length-encoded image masks
Author-email: István Sárándi <istvan.sarandi@uni-tuebingen.de>
License: Copyright (c) 2023-2025, Istvan Sarandi
Project-URL: Homepage, https://github.com/isarandi/rlemasklib
Project-URL: Repository, https://github.com/isarandi/rlemasklib
Project-URL: Documentation, https://rlemasklib.readthedocs.io/
Project-URL: Issues, https://github.com/isarandi/rlemasklib/issues
Project-URL: Changelog, https://github.com/isarandi/rlemasklib/releases
Project-URL: Author, https://istvansarandi.com
Keywords: computer-vision,cython,image-processing,segmentation,run-length-encoding,rle,image-segmentation,mask,compression-algorithm,image-mask,runlengthencoding,run-length,image-masking
Classifier: Development Status :: 4 - Beta
Classifier: Intended Audience :: Developers
Classifier: Intended Audience :: Science/Research
Classifier: Topic :: Scientific/Engineering :: Image Processing
Classifier: Topic :: Software Development :: Libraries
Classifier: License :: OSI Approved :: MIT License
Classifier: Programming Language :: Python
Classifier: Programming Language :: C
Classifier: Programming Language :: Cython
Classifier: Operating System :: POSIX :: Linux
Requires-Python: >=3.8
License-File: LICENSE
Requires-Dist: numpy
Dynamic: license-file
